janis_core/__init__.py
janis_core/__meta__.py
janis_core/code/__init__.py
janis_core/code/codetool.py
janis_core/code/pythontool.py
janis_core/deps/__init__.py
janis_core/graph/__init__.py
janis_core/graph/node.py
janis_core/graph/steptaginput.py
janis_core/hints/__init__.py
janis_core/ingestion/__init__.py
janis_core/ingestion/fromcwl.py
janis_core/ingestion/fromwdl.py
janis_core/operators/__init__.py
janis_core/operators/logical.py
janis_core/operators/operator.py
janis_core/operators/selectors.py
janis_core/operators/standard.py
janis_core/operators/stringformatter.py
janis_core/tests/__init__.py
janis_core/tests/test_commandtool.py
janis_core/tests/test_conditionals.py
janis_core/tests/test_from_cwl.py
janis_core/tests/test_from_wdl.py
janis_core/tests/test_generics_util.py
janis_core/tests/test_logger.py
janis_core/tests/test_metadata.py
janis_core/tests/test_operators.py
janis_core/tests/test_python_tool.py
janis_core/tests/test_receivefrom.py
janis_core/tests/test_running.py
janis_core/tests/test_secondary.py
janis_core/tests/test_step.py
janis_core/tests/test_stringbuilder.py
janis_core/tests/test_test_runner.py
janis_core/tests/test_tools.py
janis_core/tests/test_translation.py
janis_core/tests/test_translation_cwl.py
janis_core/tests/test_translation_janis.py
janis_core/tests/test_translation_nextflow.py
janis_core/tests/test_translation_wdl.py
janis_core/tests/test_types.py
janis_core/tests/test_validateinputvalue.py
janis_core/tests/test_validators.py
janis_core/tests/test_workflow.py
janis_core/tests/tests_util.py
janis_core/tests/testtools.py
janis_core/tests/integration/__init__.py
janis_core/tests/integration/test_directorygenerator.py
janis_core/tool/__init__.py
janis_core/tool/batchrun.py
janis_core/tool/commandtool.py
janis_core/tool/cwl_tool_parser.py
janis_core/tool/documentation.py
janis_core/tool/test_classes.py
janis_core/tool/test_definitions.py
janis_core/tool/test_helpers.py
janis_core/tool/test_suite_runner.py
janis_core/tool/tool.py
janis_pipelines.core-0.12.1.dist-info/LICENSE
janis_pipelines.core-0.12.1.dist-info/METADATA
janis_pipelines.core-0.12.1.dist-info/WHEEL
janis_pipelines.core-0.12.1.dist-info/top_level.txt
janis_pipelines.core-0.12.1.dist-info/RECORD
