Metadata-Version: 2.1
Name: janis-pipelines.core
Version: 0.12.1
Summary: Contains classes and helpers to build a workflow, and provide options to convert to CWL / WDL
Home-page: https://github.com/PMCC-BioinformaticsCore/janis
Author: Michael Franklin, Evan Thomas, Mohammad Bhuyan
Author-email: michael.franklin@petermac.org
License: GNU
Keywords: janis,workflows,pipelines,cwl,wdl,bioinformatics
Platform: UNKNOWN
Classifier: Development Status :: 2 - Pre-Alpha
Classifier: Intended Audience :: Developers
Classifier: Intended Audience :: Science/Research
Classifier: Topic :: Scientific/Engineering
Classifier: Topic :: Scientific/Engineering :: Bio-Informatics
Requires-Dist: importlib-metadata
Requires-Dist: illusional.wdlgen (>=0.3.0)
Requires-Dist: ruamel.yaml (<=0.16.5,>=0.12.4)
Requires-Dist: tabulate
Requires-Dist: path
Requires-Dist: cwlformat (==2020.5.19)
Requires-Dist: cwl-utils (==0.11)
Requires-Dist: graphviz
Requires-Dist: nose
Requires-Dist: miniwdl
